[{"pk":1,"model":"products.category","fields":{"name":"t_shirts","friendly_name":"T-Shirts"}},{"pk":2,"model":"products.category","fields":{"name":"vests","friendly_name":"Vests"}},{"pk":3,"model":"products.category","fields":{"name":"hoodies","friendly_name":"Hoodies"}},{"pk":4,"model":"products.category","fields":{"name":"tops","friendly_name":"Tops"}},{"pk":5,"model":"products.category","fields":{"name":"joggers","friendly_name":"Joggers"}},{"pk":6,"model":"products.category","fields":{"name":"powders","friendly_name":"Powders"}},{"pk":7,"model":"products.category","fields":{"name":"vitamins","friendly_name":"Vitamins"}},{"pk":8,"model":"products.category","fields":{"name":"snacks","friendly_name":"Snacks"}},{"pk":9,"model":"products.category","fields":{"name":"memberships","friendly_name":"Memberships"}}]